.travis.yml
CHANGES.rst
CONTRIBUTORS.rst
MANIFEST.in
README.rst
base.cfg
bootstrap.py
buildout.cfg
checkouts.cfg
jenkins-base.cfg
jenkins.cfg
setup.py
sources.cfg
travis.cfg
versions.cfg
docs/LICENSE.GPL
docs/LICENSE.txt
src/collective/__init__.py
src/collective.dms.batchimport.egg-info/PKG-INFO
src/collective.dms.batchimport.egg-info/SOURCES.txt
src/collective.dms.batchimport.egg-info/dependency_links.txt
src/collective.dms.batchimport.egg-info/entry_points.txt
src/collective.dms.batchimport.egg-info/namespace_packages.txt
src/collective.dms.batchimport.egg-info/not-zip-safe
src/collective.dms.batchimport.egg-info/requires.txt
src/collective.dms.batchimport.egg-info/top_level.txt
src/collective/dms/__init__.py
src/collective/dms/batchimport/__init__.py
src/collective/dms/batchimport/batchimport.py
src/collective/dms/batchimport/configure.zcml
src/collective/dms/batchimport/controlpanel.pt
src/collective/dms/batchimport/fileimporter.py
src/collective/dms/batchimport/script.py
src/collective/dms/batchimport/testing.py
src/collective/dms/batchimport/testing.zcml
src/collective/dms/batchimport/upload_folder_icon.png
src/collective/dms/batchimport/utils.py
src/collective/dms/batchimport/locales/collective.dms.batchimport.pot
src/collective/dms/batchimport/locales/plone.pot
src/collective/dms/batchimport/locales/update.sh
src/collective/dms/batchimport/locales/fr/LC_MESSAGES/collective.dms.batchimport.po
src/collective/dms/batchimport/locales/fr/LC_MESSAGES/plone.po
src/collective/dms/batchimport/profiles/default/collective_dms_batchimport_marker.txt
src/collective/dms/batchimport/profiles/default/controlpanel.xml
src/collective/dms/batchimport/profiles/default/metadata.xml
src/collective/dms/batchimport/profiles/default/registry.xml
src/collective/dms/batchimport/profiles/default/rolemap.xml
src/collective/dms/batchimport/profiles/testing/collective_dms_batchimport_marker.txt
src/collective/dms/batchimport/profiles/testing/controlpanel.xml
src/collective/dms/batchimport/profiles/testing/metadata.xml
src/collective/dms/batchimport/profiles/testing/registry.xml
src/collective/dms/batchimport/tests/__init__.py
src/collective/dms/batchimport/tests/test_setup.py