Metadata-Version: 2.1
Name: collective.dms.batchimport
Version: 1.3.1
Summary: Batch import of files into the Documents Management System
Home-page: UNKNOWN
Author: Cedric Messiant
Author-email: dev@imio.be
License: gpl
Project-URL: PyPI, https://pypi.python.org/project/collective.dms.batchimport
Project-URL: Source, https://github.com/collective/collective.dms.batchimport
Keywords: Python Zope Plone
Platform: UNKNOWN
Classifier: Development Status :: 5 - Production/Stable
Classifier: Environment :: Web Environment
Classifier: Framework :: Plone
Classifier: Framework :: Plone :: 4.2
Classifier: Framework :: Plone :: 4.3
Classifier: Operating System :: OS Independent
Classifier: Programming Language :: Python
Classifier: Programming Language :: Python :: 2
Classifier: Programming Language :: Python :: 2.7
Classifier: Topic :: Software Development :: Libraries :: Python Modules
Classifier: License :: OSI Approved :: GNU General Public License v2 (GPLv2)
Provides-Extra: test
